Workbook

Sheet dda departments
A1: # | B1: Company Name | C1: Status | D1: License Volume as of 2026 | E1: Recurring
A2: 1 | B2: Central Grievance Committee
A3: 2 | B3: Community Development Authority | C3: In progress
A4: 3 | B4: Dubai Courts | C4: In progress
A5: 4 | B5: Department of Economic Development
A6: 5 | B6: Department of Economy and Tourism
A7: 6 | B7: Department of Finance | C7: In progress
A8: 7 | B8: Department of Tourism and Commerce Marketing
A9: 8 | B9: Digital Dubai Authority | C9: Customer | D9: VIP Project (50 users) | E9: VIP Project - 163,201.60 (Subscription) + 63,397.00 AED (Support Services)
B10: Digital Dubai Authority | C10: Customer | D10: Shared Sign (100 users) | E10: Shared Sign - 293,444.33 (Subscription) + 75,000.00 (Support Services)
A11: 9 | B11: Directorate General of Dubai Civil Defense
A12: 10 | B12: Dubai Academic Health Corporation
A13: 11 | B13: Dubai Air Navigation Services
A14: 12 | B14: Dubai Airport Freezone
A15: 13 | B15: Dubai Airports
A16: 14 | B16: Dubai Chambers
A17: 15 | B17: Dubai Civil Aviaition Authority
A18: 16 | B18: Dubai Civil Defence
A19: 17 | B19: Dubai Corporation for Ambulances Services | C19: Customer | D19: Business, 10k transactions (while having 275 registered users) | E19: 147,268.13 AED (end user)
A20: 18 | B20: Dubai Corporation for Aviation Engineering Projects | C20: In progress
A21: 19 | B21: Dubai Culture & Arts Authority | C21: Customer | D21: DigiSign, 25 users | E21: 110,988.75 AED
A22: 20 | B22: Dubai Customs | C22: In progress
A23: 21 | B23: Dubai Duty Free
A24: 22 | B24: Dubai Economy and Tourism | C24: Lost
A25: 23 | B25: Dubai Electricity & Water Authority (DEWA) | C25: In progress
A26: 24 | B26: Dubai Electronic Security Center | C26: Customer | D26: Ultimate, 60 users | E26: 234,635.43 AED
A27: 25 | B27: Dubai Export Development Coroporation
A28: 26 | B28: Dubai Financial Market (DFM)
A29: 27 | B29: Dubai Foundation for Women and Children
A30: 28 | B30: Dubai Future Foundation
A31: 29 | B31: Dubai Government Human Resource Department
A32: 30 | B32: Dubai Government Workshop
A33: 31 | B33: Dubai Health | C33: In progress
A34: 32 | B34: Dubai Health Authority (DHA) | C34: In progress
A35: 33 | B35: Dubai International Financial Centre (DIFC) | C35: Docusign
A36: 34 | B36: Dubai Islamic Economy Development Centre
A37: 35 | B37: Dubai Judicial Institute
A38: 36 | B38: Dubai Land Department (DLD) | C38: important
A39: 37 | B39: Dubai Maritime City Authority
A40: 38 | B40: Dubai Media Council
A41: 39 | B41: Dubai Media Inc
A42: 40 | B42: Dubai Municipality | C42: In progress
A43: 41 | B43: Dubai Petroleum | C43: Docusign
A44: 42 | B44: Dubai Police
A45: 43 | B45: Dubai Public Prosecution
A46: 44 | B46: Dubai Silicon Oasis Authority
A47: 45 | B47: Dubai South | C47: Docusign
A48: 46 | B48: Dubai Sports Council
A49: 47 | B49: Dubai Statistics Center
A50: 40 | B50: Dubai Municipality | C50: In progress
A51: 49 | B51: Dubai Women Establishment
A52: 50 | B52: Economic Security Center of Dubai
A53: 51 | B53: Emirates International Accreditation Centre (eiac)
A54: 52 | B54: Endowment And Minor Trust Foundation
A55: 53 | B55: Financial Audit Authority | C55: AdobeSign
A56: 54 | B56: General Directorate of Residency and Forigners Affairs - Dubai
A57: 55 | B57: Hamdan Bin Mohammed Smart University
A58: 56 | B58: International City for Humanitarian Services
A59: 57 | B59: Investment Corporation of Dubai | C59: Customer | D59: Ultimate, 150 users | E59: 177,108.00 AED
A60: 58 | B60: Islamic Affairs & Charitable Activities Department (Awqaf Dubai)
A61: 59 | B61: Jabel Ali Free Zone
A62: 60 | B62: Khbrati
A63: 61 | B63: Knowledge and Human Development Authority
A64: 62 | B64: Knowledge Fund Foundation
A65: 63 | B65: Mohamed Bin Rashid Space Centre
A66: 64 | B66: Mohammed Bin Rashid Al Maktoum Knowledge Foundation
A67: 65 | B67: Mohammed Bin Rashid Al Maktoum Library Foundation
A68: 66 | B68: Mohammed Bin Rashid Housing Establishment | C68: In progress
A69: 67 | B69: Mohammed Bin Rashid School of Government
A70: 68 | B70: National Bonds
A71: 69 | B71: Nedaa - Professional Communication Corporation
A72: 70 | B72: Ports, Customs and Free Zone Corporation (PCFC) | C72: Customer | D72: Business, 20 users (renewal will be for approx. 30 users) | E72: 116,564.92 AED (end user)
A73: 71 | B73: Professional Communication Corporation 'Nedaa'
A74: 72 | B74: Protocol Department
A75: 73 | B75: Public Prosecution
A76: 74 | B76: Roads and Transport Authority (RTA) | C76: Customer | D76: AMC, 1k users (+discussion about Sovereign Workspace extension) | E76: 608,000.00 AED (end user)
A77: 75 | B77: Security Industry Regulatory Authority
A78: 76 | B78: State Security - Dubai
A79: 77 | B79: Supreme Council of Energy Dubai
A80: 78 | B80: Supreme Legislation Committee | C80: In progress
A81: 79 | B81: The Executive Council - Dubai | C81: AdobeSign
A82: 80 | B82: The Governement of Dubai Human Resources Department
A83: 81 | B83: The Government of Dubai Legal Affairs Department
A84: 82 | B84: The Government of Dubai Media Office
A85: 83 | B85: The Supreme Legislation Committee
A86: 84 | B86: Trakhees Corporation
A87: 85 | B87: UAE Food Bank
A88: 86 | B88: Visit Dubai
A89: 87 | B89: Emirates Integrated Telecommunications Company (du)
A90: 88 | B90: Mohammed Bin Rashid Al Maktoum Global Initiatives
A91: 89 | B91: Mohammed Bin Rashid Centre for Government Innovation - Dubai
A92: 90 | B92: Sheikh Zayed Housing Programme
A93: 91 | B93: Dubai Healthcare City Authority | C93: Customer | D93: Enterprise, 5k transactions (while having 150 registered users) | E93: 57,627.5 AED (end user)

Sheet pricing
C1: DDA Shared Service Special Discount | D1: DDA Shared Service Discount Tier Discount
C2: 20,00% | D2: 5,00% | E2: 5,00% | F2: 10,00% | G2: 10,00% | H2: 15,00%
C3: Total Discount | D3: 25,00% | E3: 30,00% | F3: 40,00% | G3: 50,00% | H3: 60,00%
D4: Tier 1 | E4: Tier 2 | F4: Tier 3 | G4: Tier 4 | H4: Tier 5
B5: End Discounted User Price (Annual Subscription) | C5: Enteprise DDA Shared Service Price | D5: Min 100 users up to 499 users | E5: Min 500 users up to 999 users | F5: Min 1000 users up to 1999 users | G5: Min 2000 users up to 2999 users | H5: Min 3000 users
A6: Regular Users (unlimited transactions) price per user per year in AED | B6: AED 2 950 | C6: AED 2 360 | D6: AED 2 213 | E6: AED 2 065 | F6: AED 1 770 | G6: AED 1 475 | H6: =2950*0.4 -> 1180
D14: Min 10 000 transactions up to 39 999 transactions | E14: Min 40 000 transactions up to 99 999 transactions | F14: Min 100 000 transactions up to 299 999 transactions | G14: Min 300 000 transactions up to 799 999 transactions | H14: Min 800 000 transactions
A15: API Transaction price in AED | B15: AED 10,50 | C15: AED 8,40 | D15: AED 7,88 | E15: AED 7,35 | F15: AED 6,30 | G15: AED 5,25 | H15: AED 3,68
A18: Supporting Hours | C18: Min. annual support costs
A19: Plus Support Plan 8x5: 8 hours (8:30 am to 4:30 pm Central European Time) 5 days (Monday to Friday, excluding Non-Support Days) | C19: AED 55 000 | D19: AED 55 000 | E19: AED 144 550 | F19: AED 247 800 | G19: AED 413 000 | H19: AED 433 650
A20: Plus Support Plan 24x7: 24 hours excluding Non-Support Days | C20: AED 75 000 | D20: AED 75 000 | E20: AED 206 500 | F20: AED 354 000 | G20: AED 590 000 | H20: AED 619 500
A22: One time onboarding fees per organisation | C22: AED 25 000
A24: Other modules available : | B24: DMS, eCorrespondence
B26: Sample Calculation | C26: Purchased Users | D26: Purchase Price
B27: 1st Purchase Order - 150 Users | C27: 150 | D27: AED 331 875
B28: 2nd Purchase Order 550 User | C28: 550 | D28: AED 1 135 750
B29: Total Subscription Value | C29: 700 | D29: AED 1 467 625
B31: Note: Renewals are calculated based on total subscription value at the time of initial purchase as shown above

Sheet Sheet4

Sheet survey 2026
A1: # | B1: Survey Question | C1: Response | D1: Responses | E1: %
A2: 1 | B2: Does your organization currently use a digital/electronic signature system? | C2: Yes | D2: 21 | E2: 0.5526
C3: No | D3: 10 | E3: 0.2632
C4: Under planning | D4: 6 | E4: 0.1579
C5: Under implementation | D5: 1 | E5: 0.0263
C6: Total | D6: 38 | E6: 1
A7: 2 | B7: Which digital signature system is currently used / being implemented? | C7: Circularo Digital Sign | D7: 6 | E7: 0.2727
C8: Adobe Sign | D8: 5 | E8: 0.2273
C9: DocuSign | D9: 2 | E9: 0.0909
C10: Other | D10: 9 | E10: 0.4091
C11: Total | D11: 22 | E11: 1
A12: 2a | B12: Other systems specified | C12: d2tick | D12: 2 | E12: —
C13: signeasy | D13: 2 | E13: —
C14: Ascertia SigningHub | D14: 1 | E14: —
C15: DocuSign & Adobe Sign | D15: 1 | E15: —
C16: emSigner | D16: 1 | E16: —
C17: Kofax SignDoc | D17: 1 | E17: —
C18: Tungsten (Kofax) SignDoc | D18: 1 | E18: —
A19: 3 | B19: Current / expected number of digital signature users when implementation is complete | C19: 1–50 users | D19: 6 | E19: 0.2727
C20: 51–100 users | D20: 4 | E20: 0.1818
C21: 101–500 users | D21: 7 | E21: 0.3182
C22: More than 1,000 users | D22: 4 | E22: 0.1818
C23: Other | D23: 1 | E23: 0.0455
C24: Total | D24: 22 | E24: 1
A25: 4 | B25: Approximate annual cost of the current / expected digital signature system | C25: Less than AED 50,000 | D25: 7 | E25: 0.3182
C26: AED 50,001–100,000 | D26: 6 | E26: 0.2727
C27: AED 100,001–250,000 | D27: 6 | E27: 0.2727
C28: AED 250,001–500,000 | D28: 1 | E28: 0.0455
C29: More than AED 2,000,000 | D29: 1 | E29: 0.0455
C30: Not available / unknown | D30: 1 | E30: 0.0455
C31: Total | D31: 22 | E31: 1
A32: 5 | B32: Do you expect digital signature usage to increase in the future? | C32: Yes – moderate increase expected | D32: 11 | E32: 0.5
C33: Yes – significant increase expected | D33: 6 | E33: 0.2727
C34: Unsure / to be determined | D34: 1 | E34: 0.0455
C35: No – expected to remain approximately the same | D35: 4 | E35: 0.1818
C36: Total | D36: 22 | E36: 1
A37: 6 | B37: What factors are expected to drive this increase? | C37: Increase in number of users | D37: 13 | E37: 0.7647
C38: Expansion to additional departments | D38: 10 | E38: 0.5882
C39: Increased external signing with suppliers, partners, customers/public | D39: 10 | E39: 0.5882
C40: New document types / new use cases | D40: 9 | E40: 0.5294
C41: Other | D41: 0 | E41: 0
A42: 7 | B42: Would your organization be interested in using a digital signature system? | C42: Yes – we have a current requirement | D42: 10 | E42: 0.625
C43: Yes – may need it in the future | D43: 6 | E43: 0.375
C44: Total interested organizations | D44: 16 | E44: 1
A45: 8 | B45: What is the primary use of digital/electronic signature in your organization, or expected use if implemented? | C45: Both internal and external | D45: 26 | E45: 0.6842
C46: Internal – document approval/signing between departments or employees | D46: 10 | E46: 0.2632
C47: External – signing documents with suppliers, partners, customers/public | D47: 2 | E47: 0.0526
C48: Total | D48: 38 | E48: 1
B53: Strong management-level takeaways
B55: For your Digital Dubai management presentation, I would reduce this further to five headline figures:
B57: 38 Dubai Government entities surveyed → 21 already use digital signature → 16 additional entities expressed demand → 77% of existing users expect usage to grow → 76% say growth will be driven by more users.
B59: The particularly useful commercial point is that the survey shows demand beyond the current installed base: 10 entities say they have a requirement now, with another 6 indicating future need. Also, among the 22 organizations already using or implementing digital signature, 7 are in the 101–500 user range and 4 report more than 1,000 users. This supports the case that centralized licensing needs to accommodate several thousand additional users rather than only today's installed base.
B62: User range | C62: Entities | D62: Minimum users | E62: Maximum users*
B63: 1–50 | C63: 6 | D63: 6 | E63: 300
B64: 51–100 | C64: 4 | D64: 204 | E64: 400
B65: 101–500 | C65: 7 | D65: 707 | E65: 3500
B66: More than 1,000 | C66: 4 | D66: 4004 | E66: No stated maximum
B67: Other | C67: 1 | D67: Unknown | E67: Unknown
B68: Total | C68: 22 | D68: at least 4,921 | E68: Not bounded by survey

Sheet Executive Summary
A1: Digital Dubai – Central Digital Signature Licensing Model
A3: Entities in master list | B3: 91
A4: Estimated employees | B4: ='91 Entities Model'!D93 -> 165227
A5: Estimated potential digital-sign users | B5: ='91 Entities Model'!G93 -> 61482
A6: Central Tier 5 price / user | B6: 1180
A7: Annual fragmented license cost | B7: ='91 Entities Model'!K93 -> 102939175
A8: Annual central Tier 5 cost | B8: ='91 Entities Model'!L93 -> 72548760
A9: Annual saving | B9: ='91 Entities Model'!M93 -> 30390415
A10: 5-year saving vs fragmented tiers | B10: ='91 Entities Model'!N93 -> 151952075
A11: 5-year saving vs AED 2,950 regular price | B11: ='91 Entities Model'!O93 -> 362743800
A13: Investor revenue opportunity (eSign + adjacent products) | B13: Potential Value
A14: Potential annual eSign revenue | B14: ='Investor Deal Potential'!B9 -> 72548760
A15: Additional storage + collaboration + AI revenue (~50%) | B15: ='Investor Deal Potential'!B11 -> 36274380
A16: Potential annual total revenue | B16: ='Investor Deal Potential'!B12 -> 108823140
A17: Potential 5-year total deal value | B17: ='Investor Deal Potential'!B15 -> 544115700
A19: Product opportunity: eSign is the core subscription. Secure document storage, collaboration and AI can add approximately 50% revenue on top of eSign, creating a broader sovereign digital-workspace opportunity. The 50% uplift is an illustrative commercial assumption for investor sizing, not committed revenue.
A22: Important: employee counts marked as planning estimates should be validated before external/client use. The model is designed for management sizing and can be updated as official figures are confirmed.

Sheet Investor Deal Potential
A1: Digital Dubai – Investor Deal Potential
A2: Potential 5-year revenue opportunity across the 91-entity Dubai Government portfolio
A4: Portfolio sizing | B4: Value | C4: Notes
A5: Entities in addressable portfolio | B5: ='Executive Summary'!B3 -> 91 | C5: 91 entities in current master list
A6: Estimated employees | B6: ='91 Entities Model'!D93 -> 165227 | C6: Planning estimate / published figures where available
A7: Potential eSign users | B7: ='91 Entities Model'!G93 -> 61482 | C7: Addressable digital-signature users from current model
A8: eSign price per user / year | B8: ='Pricing & Assumptions'!B9 -> 1180 | C8: Tier 5 centralized DDA shared-service price
A9: Potential annual eSign revenue | B9: =B7*B8 -> 72548760 | C9: Core eSign subscription
A10: Adjacent product revenue uplift | B10: 0.5 | C10: Secure document storage + collaboration + AI
A11: Potential annual adjacent revenue | B11: =B9*B10 -> 36274380 | C11: Approx. 50% additional revenue opportunity
A12: Potential annual total revenue | B12: =B9+B11 -> 108823140 | C12: eSign + adjacent products
A13: Potential 5-year eSign revenue | B13: =B9*5 -> 362743800 | C13: Before inflation / expansion
A14: Potential 5-year adjacent revenue | B14: =B11*5 -> 181371900 | C14: Storage + collaboration + AI
A15: Potential 5-year total deal value | B15: =B12*5 -> 544115700 | C15: Illustrative revenue opportunity
A18: Scale illustration
A19: Potential Users | B19: Annual eSign Revenue | C19: Adjacent Products (+50%) | D19: Annual Total Revenue | E19: 5-Year Total Revenue
A20: 3000 | B20: =A20*$B$8 -> 3540000 | C20: =B20*$B$10 -> 1770000 | D20: =B20+C20 -> 5310000 | E20: =D20*5 -> 26550000
A21: 5000 | B21: =A21*$B$8 -> 5900000 | C21: =B21*$B$10 -> 2950000 | D21: =B21+C21 -> 8850000 | E21: =D21*5 -> 44250000
A22: 10000 | B22: =A22*$B$8 -> 11800000 | C22: =B22*$B$10 -> 5900000 | D22: =B22+C22 -> 17700000 | E22: =D22*5 -> 88500000
A23: 25000 | B23: =A23*$B$8 -> 29500000 | C23: =B23*$B$10 -> 14750000 | D23: =B23+C23 -> 44250000 | E23: =D23*5 -> 221250000
A24: Current model potential | B24: =A24*$B$8 -> #VALUE! | C24: =B24*$B$10 -> #VALUE! | D24: =B24+C24 -> #VALUE! | E24: =D24*5 -> #VALUE!
A27: Investor framing: eSign is the core product. Secure document storage, collaboration and AI represent an estimated additional revenue opportunity of approximately 50% on top of eSign revenue. This is an illustrative commercial sizing assumption, not committed revenue, and excludes implementation, support, VAT, inflation and future user growth.

Sheet 91 Entities Model
A1: # | B1: Entity | C1: Status | D1: Estimated Employees | E1: Employee Figure Basis | F1: Potential Sign Users % | G1: Potential Digital Sign Users | H1: Known Current Users | I1: Current Fragmented Price / User (AED) | J1: Central Tier 5 Price / User (AED) | K1: Annual Cost - Fragmented (AED) | L1: Annual Cost - Central Tier 5 (AED) | M1: Annual Saving (AED) | N1: 5-Year Saving (AED) | O1: 5-Year Saving vs Regular AED 2,950 | P1: Source / Note
A2: 1 | B2: Central Grievance Committee | D2: 80 | E2: Planning estimate – validate with entity | F2: 0.5 | G2: =ROUND(D2*F2,0) -> 40 | I2: =IF(G2<100,2950,IF(G2<500,2213,IF(G2<1000,2065,IF(G2<2000,1770,IF(G2<3000,1475,1180))))) -> 2950 | J2: ='Pricing & Assumptions'!$B$9 -> 1180 | K2: =G2*I2 -> 118000 | L2: =G2*J2 -> 47200 | M2: =K2-L2 -> 70800 | N2: =M2*5 -> 354000 | O2: =G2*('Pricing & Assumptions'!$B$3-'Pricing & Assumptions'!$B$9)*5 -> 236000 | P2: Indicative planning estimate; replace with official headcount when available
A3: 2 | B3: Community Development Authority | C3: In progress | D3: 500 | E3: Planning estimate – validate with entity | F3: 0.5 | G3: =ROUND(D3*F3,0) -> 250 | I3: =IF(G3<100,2950,IF(G3<500,2213,IF(G3<1000,2065,IF(G3<2000,1770,IF(G3<3000,1475,1180))))) -> 2213 | J3: ='Pricing & Assumptions'!$B$9 -> 1180 | K3: =G3*I3 -> 553250 | L3: =G3*J3 -> 295000 | M3: =K3-L3 -> 258250 | N3: =M3*5 -> 1291250 | O3: =G3*('Pricing & Assumptions'!$B$3-'Pricing & Assumptions'!$B$9)*5 -> 1475000 | P3: Indicative planning estimate; replace with official headcount when available
A4: 3 | B4: Dubai Courts | C4: In progress | D4: 1410 | E4: Planning estimate – validate with entity | F4: 0.7 | G4: =ROUND(D4*F4,0) -> 987 | I4: =IF(G4<100,2950,IF(G4<500,2213,IF(G4<1000,2065,IF(G4<2000,1770,IF(G4<3000,1475,1180))))) -> 2065 | J4: ='Pricing & Assumptions'!$B$9 -> 1180 | K4: =G4*I4 -> 2038155 | L4: =G4*J4 -> 1164660 | M4: =K4-L4 -> 873495 | N4: =M4*5 -> 4367475 | O4: =G4*('Pricing & Assumptions'!$B$3-'Pricing & Assumptions'!$B$9)*5 -> 5823300 | P4: Indicative planning estimate; replace with official headcount when available
A5: 4 | B5: Department of Economic Development | D5: 900 | E5: Planning estimate – validate with entity | F5: 0.5 | G5: =ROUND(D5*F5,0) -> 450 | I5: =IF(G5<100,2950,IF(G5<500,2213,IF(G5<1000,2065,IF(G5<2000,1770,IF(G5<3000,1475,1180))))) -> 2213 | J5: ='Pricing & Assumptions'!$B$9 -> 1180 | K5: =G5*I5 -> 995850 | L5: =G5*J5 -> 531000 | M5: =K5-L5 -> 464850 | N5: =M5*5 -> 2324250 | O5: =G5*('Pricing & Assumptions'!$B$3-'Pricing & Assumptions'!$B$9)*5 -> 2655000 | P5: Indicative planning estimate; replace with official headcount when available
A6: 5 | B6: Department of Economy and Tourism | D6: 1200 | E6: Planning estimate – validate with entity | F6: 0.5 | G6: =ROUND(D6*F6,0) -> 600 | I6: =IF(G6<100,2950,IF(G6<500,2213,IF(G6<1000,2065,IF(G6<2000,1770,IF(G6<3000,1475,1180))))) -> 2065 | J6: ='Pricing & Assumptions'!$B$9 -> 1180 | K6: =G6*I6 -> 1239000 | L6: =G6*J6 -> 708000 | M6: =K6-L6 -> 531000 | N6: =M6*5 -> 2655000 | O6: =G6*('Pricing & Assumptions'!$B$3-'Pricing & Assumptions'!$B$9)*5 -> 3540000 | P6: Indicative planning estimate; replace with official headcount when available
A7: 6 | B7: Department of Finance | C7: In progress | D7: 350 | E7: Planning estimate – validate with entity | F7: 0.7 | G7: =ROUND(D7*F7,0) -> 245 | I7: =IF(G7<100,2950,IF(G7<500,2213,IF(G7<1000,2065,IF(G7<2000,1770,IF(G7<3000,1475,1180))))) -> 2213 | J7: ='Pricing & Assumptions'!$B$9 -> 1180 | K7: =G7*I7 -> 542185 | L7: =G7*J7 -> 289100 | M7: =K7-L7 -> 253085 | N7: =M7*5 -> 1265425 | O7: =G7*('Pricing & Assumptions'!$B$3-'Pricing & Assumptions'!$B$9)*5 -> 1445500 | P7: Indicative planning estimate; replace with official headcount when available
A8: 7 | B8: Department of Tourism and Commerce Marketing | D8: 600 | E8: Planning estimate – validate with entity | F8: 0.5 | G8: =ROUND(D8*F8,0) -> 300 | I8: =IF(G8<100,2950,IF(G8<500,2213,IF(G8<1000,2065,IF(G8<2000,1770,IF(G8<3000,1475,1180))))) -> 2213 | J8: ='Pricing & Assumptions'!$B$9 -> 1180 | K8: =G8*I8 -> 663900 | L8: =G8*J8 -> 354000 | M8: =K8-L8 -> 309900 | N8: =M8*5 -> 1549500 | O8: =G8*('Pricing & Assumptions'!$B$3-'Pricing & Assumptions'!$B$9)*5 -> 1770000 | P8: Indicative planning estimate; replace with official headcount when available
A9: 8 | B9: Digital Dubai Authority | C9: Customer | D9: 700 | E9: Planning estimate – validate with entity | F9: 0.7 | G9: =ROUND(D9*F9,0) -> 490 | H9: 150 | I9: =IF(G9<100,2950,IF(G9<500,2213,IF(G9<1000,2065,IF(G9<2000,1770,IF(G9<3000,1475,1180))))) -> 2213 | J9: ='Pricing & Assumptions'!$B$9 -> 1180 | K9: =G9*I9 -> 1084370 | L9: =G9*J9 -> 578200 | M9: =K9-L9 -> 506170 | N9: =M9*5 -> 2530850 | O9: =G9*('Pricing & Assumptions'!$B$3-'Pricing & Assumptions'!$B$9)*5 -> 2891000 | P9: Indicative planning estimate; replace with official headcount when available
A10: 9 | B10: Directorate General of Dubai Civil Defense | D10: 3000 | E10: Planning estimate – validate with entity | F10: 0.3 | G10: =ROUND(D10*F10,0) -> 900 | I10: =IF(G10<100,2950,IF(G10<500,2213,IF(G10<1000,2065,IF(G10<2000,1770,IF(G10<3000,1475,1180))))) -> 2065 | J10: ='Pricing & Assumptions'!$B$9 -> 1180 | K10: =G10*I10 -> 1858500 | L10: =G10*J10 -> 1062000 | M10: =K10-L10 -> 796500 | N10: =M10*5 -> 3982500 | O10: =G10*('Pricing & Assumptions'!$B$3-'Pricing & Assumptions'!$B$9)*5 -> 5310000 | P10: Indicative planning estimate; replace with official headcount when available
A11: 10 | B11: Dubai Academic Health Corporation | D11: 12000 | E11: Planning estimate – validate with entity | F11: 0.3 | G11: =ROUND(D11*F11,0) -> 3600 | I11: =IF(G11<100,2950,IF(G11<500,2213,IF(G11<1000,2065,IF(G11<2000,1770,IF(G11<3000,1475,1180))))) -> 1180 | J11: ='Pricing & Assumptions'!$B$9 -> 1180 | K11: =G11*I11 -> 4248000 | L11: =G11*J11 -> 4248000 | M11: =K11-L11 -> 0 | N11: =M11*5 -> 0 | O11: =G11*('Pricing & Assumptions'!$B$3-'Pricing & Assumptions'!$B$9)*5 -> 21240000 | P11: Indicative planning estimate; replace with official headcount when available
A12: 11 | B12: Dubai Air Navigation Services | D12: 1500 | E12: Planning estimate – validate with entity | F12: 0.5 | G12: =ROUND(D12*F12,0) -> 750 | I12: =IF(G12<100,2950,IF(G12<500,2213,IF(G12<1000,2065,IF(G12<2000,1770,IF(G12<3000,1475,1180))))) -> 2065 | J12: ='Pricing & Assumptions'!$B$9 -> 1180 | K12: =G12*I12 -> 1548750 | L12: =G12*J12 -> 885000 | M12: =K12-L12 -> 663750 | N12: =M12*5 -> 3318750 | O12: =G12*('Pricing & Assumptions'!$B$3-'Pricing & Assumptions'!$B$9)*5 -> 4425000 | P12: Indicative planning estimate; replace with official headcount when available
A13: 12 | B13: Dubai Airport Freezone | D13: 700 | E13: Planning estimate – validate with entity | F13: 0.5 | G13: =ROUND(D13*F13,0) -> 350 | I13: =IF(G13<100,2950,IF(G13<500,2213,IF(G13<1000,2065,IF(G13<2000,1770,IF(G13<3000,1475,1180))))) -> 2213 | J13: ='Pricing & Assumptions'!$B$9 -> 1180 | K13: =G13*I13 -> 774550 | L13: =G13*J13 -> 413000 | M13: =K13-L13 -> 361550 | N13: =M13*5 -> 1807750 | O13: =G13*('Pricing & Assumptions'!$B$3-'Pricing & Assumptions'!$B$9)*5 -> 2065000 | P13: Indicative planning estimate; replace with official headcount when available
A14: 13 | B14: Dubai Airports | D14: 3000 | E14: Published profile (older) | F14: 0.3 | G14: =ROUND(D14*F14,0) -> 900 | I14: =IF(G14<100,2950,IF(G14<500,2213,IF(G14<1000,2065,IF(G14<2000,1770,IF(G14<3000,1475,1180))))) -> 2065 | J14: ='Pricing & Assumptions'!$B$9 -> 1180 | K14: =G14*I14 -> 1858500 | L14: =G14*J14 -> 1062000 | M14: =K14-L14 -> 796500 | N14: =M14*5 -> 3982500 | O14: =G14*('Pricing & Assumptions'!$B$3-'Pricing & Assumptions'!$B$9)*5 -> 5310000 | P14: https://summit-events.com/assets/files/PDS19_Programme_FINAL_UPDATE.pdf
A15: 14 | B15: Dubai Chambers | D15: 500 | E15: Planning estimate – validate with entity | F15: 0.7 | G15: =ROUND(D15*F15,0) -> 350 | I15: =IF(G15<100,2950,IF(G15<500,2213,IF(G15<1000,2065,IF(G15<2000,1770,IF(G15<3000,1475,1180))))) -> 2213 | J15: ='Pricing & Assumptions'!$B$9 -> 1180 | K15: =G15*I15 -> 774550 | L15: =G15*J15 -> 413000 | M15: =K15-L15 -> 361550 | N15: =M15*5 -> 1807750 | O15: =G15*('Pricing & Assumptions'!$B$3-'Pricing & Assumptions'!$B$9)*5 -> 2065000 | P15: Indicative planning estimate; replace with official headcount when available
A16: 15 | B16: Dubai Civil Aviaition Authority | D16: 500 | E16: Planning estimate – validate with entity | F16: 0.5 | G16: =ROUND(D16*F16,0) -> 250 | I16: =IF(G16<100,2950,IF(G16<500,2213,IF(G16<1000,2065,IF(G16<2000,1770,IF(G16<3000,1475,1180))))) -> 2213 | J16: ='Pricing & Assumptions'!$B$9 -> 1180 | K16: =G16*I16 -> 553250 | L16: =G16*J16 -> 295000 | M16: =K16-L16 -> 258250 | N16: =M16*5 -> 1291250 | O16: =G16*('Pricing & Assumptions'!$B$3-'Pricing & Assumptions'!$B$9)*5 -> 1475000 | P16: Indicative planning estimate; replace with official headcount when available
A17: 16 | B17: Dubai Civil Defence | D17: 3000 | E17: Planning estimate – validate with entity | F17: 0.3 | G17: =ROUND(D17*F17,0) -> 900 | I17: =IF(G17<100,2950,IF(G17<500,2213,IF(G17<1000,2065,IF(G17<2000,1770,IF(G17<3000,1475,1180))))) -> 2065 | J17: ='Pricing & Assumptions'!$B$9 -> 1180 | K17: =G17*I17 -> 1858500 | L17: =G17*J17 -> 1062000 | M17: =K17-L17 -> 796500 | N17: =M17*5 -> 3982500 | O17: =G17*('Pricing & Assumptions'!$B$3-'Pricing & Assumptions'!$B$9)*5 -> 5310000 | P17: Indicative planning estimate; replace with official headcount when available
A18: 17 | B18: Dubai Corporation for Ambulances Services | C18: Customer | D18: 1400 | E18: Planning estimate – validate with entity | F18: 0.3 | G18: =ROUND(D18*F18,0) -> 420 | H18: 275 | I18: =IF(G18<100,2950,IF(G18<500,2213,IF(G18<1000,2065,IF(G18<2000,1770,IF(G18<3000,1475,1180))))) -> 2213 | J18: ='Pricing & Assumptions'!$B$9 -> 1180 | K18: =G18*I18 -> 929460 | L18: =G18*J18 -> 495600 | M18: =K18-L18 -> 433860 | N18: =M18*5 -> 2169300 | O18: =G18*('Pricing & Assumptions'!$B$3-'Pricing & Assumptions'!$B$9)*5 -> 2478000 | P18: Indicative planning estimate; replace with official headcount when available
A19: 18 | B19: Dubai Corporation for Aviation Engineering Projects | C19: In progress | D19: 500 | E19: Planning estimate – validate with entity | F19: 0.5 | G19: =ROUND(D19*F19,0) -> 250 | I19: =IF(G19<100,2950,IF(G19<500,2213,IF(G19<1000,2065,IF(G19<2000,1770,IF(G19<3000,1475,1180))))) -> 2213 | J19: ='Pricing & Assumptions'!$B$9 -> 1180 | K19: =G19*I19 -> 553250 | L19: =G19*J19 -> 295000 | M19: =K19-L19 -> 258250 | N19: =M19*5 -> 1291250 | O19: =G19*('Pricing & Assumptions'!$B$3-'Pricing & Assumptions'!$B$9)*5 -> 1475000 | P19: Indicative planning estimate; replace with official headcount when available
A20: 19 | B20: Dubai Culture & Arts Authority | C20: Customer | D20: 500 | E20: Planning estimate – validate with entity | F20: 0.7 | G20: =ROUND(D20*F20,0) -> 350 | H20: 25 | I20: =IF(G20<100,2950,IF(G20<500,2213,IF(G20<1000,2065,IF(G20<2000,1770,IF(G20<3000,1475,1180))))) -> 2213 | J20: ='Pricing & Assumptions'!$B$9 -> 1180 | K20: =G20*I20 -> 774550 | L20: =G20*J20 -> 413000 | M20: =K20-L20 -> 361550 | N20: =M20*5 -> 1807750 | O20: =G20*('Pricing & Assumptions'!$B$3-'Pricing & Assumptions'!$B$9)*5 -> 2065000 | P20: Indicative planning estimate; replace with official headcount when available
A21: 20 | B21: Dubai Customs | C21: In progress | D21: 2880 | E21: Published | F21: 0.5 | G21: =ROUND(D21*F21,0) -> 1440 | I21: =IF(G21<100,2950,IF(G21<500,2213,IF(G21<1000,2065,IF(G21<2000,1770,IF(G21<3000,1475,1180))))) -> 1770 | J21: ='Pricing & Assumptions'!$B$9 -> 1180 | K21: =G21*I21 -> 2548800 | L21: =G21*J21 -> 1699200 | M21: =K21-L21 -> 849600 | N21: =M21*5 -> 4248000 | O21: =G21*('Pricing & Assumptions'!$B$3-'Pricing & Assumptions'!$B$9)*5 -> 8496000 | P21: https://www.dubaicustoms.gov.ae/en/SocialResponsibility/Csr/OurEmployees/Pages/default.aspx
A22: 21 | B22: Dubai Duty Free | D22: 5800 | E22: Published 2025 | F22: 0.3 | G22: =ROUND(D22*F22,0) -> 1740 | I22: =IF(G22<100,2950,IF(G22<500,2213,IF(G22<1000,2065,IF(G22<2000,1770,IF(G22<3000,1475,1180))))) -> 1770 | J22: ='Pricing & Assumptions'!$B$9 -> 1180 | K22: =G22*I22 -> 3079800 | L22: =G22*J22 -> 2053200 | M22: =K22-L22 -> 1026600 | N22: =M22*5 -> 5133000 | O22: =G22*('Pricing & Assumptions'!$B$3-'Pricing & Assumptions'!$B$9)*5 -> 10266000 | P22: https://icd.gov.ae/wp-content/uploads/2025/11/ICD-AR2025-Full-Report-2.pdf
A23: 22 | B23: Dubai Economy and Tourism | C23: Lost | D23: 1200 | E23: Planning estimate – validate with entity | F23: 0.5 | G23: =ROUND(D23*F23,0) -> 600 | I23: =IF(G23<100,2950,IF(G23<500,2213,IF(G23<1000,2065,IF(G23<2000,1770,IF(G23<3000,1475,1180))))) -> 2065 | J23: ='Pricing & Assumptions'!$B$9 -> 1180 | K23: =G23*I23 -> 1239000 | L23: =G23*J23 -> 708000 | M23: =K23-L23 -> 531000 | N23: =M23*5 -> 2655000 | O23: =G23*('Pricing & Assumptions'!$B$3-'Pricing & Assumptions'!$B$9)*5 -> 3540000 | P23: Indicative planning estimate; replace with official headcount when available
A24: 23 | B24: Dubai Electricity & Water Authority (DEWA) | C24: In progress | D24: 10722 | E24: Published 2024 | F24: 0.3 | G24: =ROUND(D24*F24,0) -> 3217 | I24: =IF(G24<100,2950,IF(G24<500,2213,IF(G24<1000,2065,IF(G24<2000,1770,IF(G24<3000,1475,1180))))) -> 1180 | J24: ='Pricing & Assumptions'!$B$9 -> 1180 | K24: =G24*I24 -> 3796060 | L24: =G24*J24 -> 3796060 | M24: =K24-L24 -> 0 | N24: =M24*5 -> 0 | O24: =G24*('Pricing & Assumptions'!$B$3-'Pricing & Assumptions'!$B$9)*5 -> 18980300 | P24: https://www.dewa.gov.ae/-/media/Images/Investor-Relations/Integrated-reports/Integrated_report_for_the_year_2024.ashx
A25: 24 | B25: Dubai Electronic Security Center | C25: Customer | D25: 250 | E25: Planning estimate – validate with entity | F25: 0.7 | G25: =ROUND(D25*F25,0) -> 175 | H25: 60 | I25: =IF(G25<100,2950,IF(G25<500,2213,IF(G25<1000,2065,IF(G25<2000,1770,IF(G25<3000,1475,1180))))) -> 2213 | J25: ='Pricing & Assumptions'!$B$9 -> 1180 | K25: =G25*I25 -> 387275 | L25: =G25*J25 -> 206500 | M25: =K25-L25 -> 180775 | N25: =M25*5 -> 903875 | O25: =G25*('Pricing & Assumptions'!$B$3-'Pricing & Assumptions'!$B$9)*5 -> 1032500 | P25: Indicative planning estimate; replace with official headcount when available
A26: 25 | B26: Dubai Export Development Coroporation | D26: 150 | E26: Planning estimate – validate with entity | F26: 0.5 | G26: =ROUND(D26*F26,0) -> 75 | I26: =IF(G26<100,2950,IF(G26<500,2213,IF(G26<1000,2065,IF(G26<2000,1770,IF(G26<3000,1475,1180))))) -> 2950 | J26: ='Pricing & Assumptions'!$B$9 -> 1180 | K26: =G26*I26 -> 221250 | L26: =G26*J26 -> 88500 | M26: =K26-L26 -> 132750 | N26: =M26*5 -> 663750 | O26: =G26*('Pricing & Assumptions'!$B$3-'Pricing & Assumptions'!$B$9)*5 -> 442500 | P26: Indicative planning estimate; replace with official headcount when available
A27: 26 | B27: Dubai Financial Market (DFM) | D27: 500 | E27: Planning estimate – validate with entity | F27: 0.7 | G27: =ROUND(D27*F27,0) -> 350 | I27: =IF(G27<100,2950,IF(G27<500,2213,IF(G27<1000,2065,IF(G27<2000,1770,IF(G27<3000,1475,1180))))) -> 2213 | J27: ='Pricing & Assumptions'!$B$9 -> 1180 | K27: =G27*I27 -> 774550 | L27: =G27*J27 -> 413000 | M27: =K27-L27 -> 361550 | N27: =M27*5 -> 1807750 | O27: =G27*('Pricing & Assumptions'!$B$3-'Pricing & Assumptions'!$B$9)*5 -> 2065000 | P27: Indicative planning estimate; replace with official headcount when available
A28: 27 | B28: Dubai Foundation for Women and Children | D28: 300 | E28: Planning estimate – validate with entity | F28: 0.5 | G28: =ROUND(D28*F28,0) -> 150 | I28: =IF(G28<100,2950,IF(G28<500,2213,IF(G28<1000,2065,IF(G28<2000,1770,IF(G28<3000,1475,1180))))) -> 2213 | J28: ='Pricing & Assumptions'!$B$9 -> 1180 | K28: =G28*I28 -> 331950 | L28: =G28*J28 -> 177000 | M28: =K28-L28 -> 154950 | N28: =M28*5 -> 774750 | O28: =G28*('Pricing & Assumptions'!$B$3-'Pricing & Assumptions'!$B$9)*5 -> 885000 | P28: Indicative planning estimate; replace with official headcount when available
A29: 28 | B29: Dubai Future Foundation | D29: 500 | E29: Planning estimate – validate with entity | F29: 0.7 | G29: =ROUND(D29*F29,0) -> 350 | I29: =IF(G29<100,2950,IF(G29<500,2213,IF(G29<1000,2065,IF(G29<2000,1770,IF(G29<3000,1475,1180))))) -> 2213 | J29: ='Pricing & Assumptions'!$B$9 -> 1180 | K29: =G29*I29 -> 774550 | L29: =G29*J29 -> 413000 | M29: =K29-L29 -> 361550 | N29: =M29*5 -> 1807750 | O29: =G29*('Pricing & Assumptions'!$B$3-'Pricing & Assumptions'!$B$9)*5 -> 2065000 | P29: Indicative planning estimate; replace with official headcount when available
A30: 29 | B30: Dubai Government Human Resource Department | D30: 400 | E30: Planning estimate – validate with entity | F30: 0.7 | G30: =ROUND(D30*F30,0) -> 280 | I30: =IF(G30<100,2950,IF(G30<500,2213,IF(G30<1000,2065,IF(G30<2000,1770,IF(G30<3000,1475,1180))))) -> 2213 | J30: ='Pricing & Assumptions'!$B$9 -> 1180 | K30: =G30*I30 -> 619640 | L30: =G30*J30 -> 330400 | M30: =K30-L30 -> 289240 | N30: =M30*5 -> 1446200 | O30: =G30*('Pricing & Assumptions'!$B$3-'Pricing & Assumptions'!$B$9)*5 -> 1652000 | P30: Indicative planning estimate; replace with official headcount when available
A31: 30 | B31: Dubai Government Workshop | D31: 1200 | E31: Planning estimate – validate with entity | F31: 0.3 | G31: =ROUND(D31*F31,0) -> 360 | I31: =IF(G31<100,2950,IF(G31<500,2213,IF(G31<1000,2065,IF(G31<2000,1770,IF(G31<3000,1475,1180))))) -> 2213 | J31: ='Pricing & Assumptions'!$B$9 -> 1180 | K31: =G31*I31 -> 796680 | L31: =G31*J31 -> 424800 | M31: =K31-L31 -> 371880 | N31: =M31*5 -> 1859400 | O31: =G31*('Pricing & Assumptions'!$B$3-'Pricing & Assumptions'!$B$9)*5 -> 2124000 | P31: Indicative planning estimate; replace with official headcount when available
A32: 31 | B32: Dubai Health | C32: In progress | D32: 15000 | E32: Planning estimate – validate with entity | F32: 0.3 | G32: =ROUND(D32*F32,0) -> 4500 | I32: =IF(G32<100,2950,IF(G32<500,2213,IF(G32<1000,2065,IF(G32<2000,1770,IF(G32<3000,1475,1180))))) -> 1180 | J32: ='Pricing & Assumptions'!$B$9 -> 1180 | K32: =G32*I32 -> 5310000 | L32: =G32*J32 -> 5310000 | M32: =K32-L32 -> 0 | N32: =M32*5 -> 0 | O32: =G32*('Pricing & Assumptions'!$B$3-'Pricing & Assumptions'!$B$9)*5 -> 26550000 | P32: Indicative planning estimate; replace with official headcount when available
A33: 32 | B33: Dubai Health Authority (DHA) | C33: In progress | D33: 2500 | E33: Planning estimate – validate with entity | F33: 0.3 | G33: =ROUND(D33*F33,0) -> 750 | I33: =IF(G33<100,2950,IF(G33<500,2213,IF(G33<1000,2065,IF(G33<2000,1770,IF(G33<3000,1475,1180))))) -> 2065 | J33: ='Pricing & Assumptions'!$B$9 -> 1180 | K33: =G33*I33 -> 1548750 | L33: =G33*J33 -> 885000 | M33: =K33-L33 -> 663750 | N33: =M33*5 -> 3318750 | O33: =G33*('Pricing & Assumptions'!$B$3-'Pricing & Assumptions'!$B$9)*5 -> 4425000 | P33: Indicative planning estimate; replace with official headcount when available
A34: 33 | B34: Dubai International Financial Centre (DIFC) | C34: DocuSign | D34: 700 | E34: Planning estimate – validate with entity | F34: 0.7 | G34: =ROUND(D34*F34,0) -> 490 | I34: =IF(G34<100,2950,IF(G34<500,2213,IF(G34<1000,2065,IF(G34<2000,1770,IF(G34<3000,1475,1180))))) -> 2213 | J34: ='Pricing & Assumptions'!$B$9 -> 1180 | K34: =G34*I34 -> 1084370 | L34: =G34*J34 -> 578200 | M34: =K34-L34 -> 506170 | N34: =M34*5 -> 2530850 | O34: =G34*('Pricing & Assumptions'!$B$3-'Pricing & Assumptions'!$B$9)*5 -> 2891000 | P34: Indicative planning estimate; replace with official headcount when available
A35: 34 | B35: Dubai Islamic Economy Development Centre | D35: 120 | E35: Planning estimate – validate with entity | F35: 0.5 | G35: =ROUND(D35*F35,0) -> 60 | I35: =IF(G35<100,2950,IF(G35<500,2213,IF(G35<1000,2065,IF(G35<2000,1770,IF(G35<3000,1475,1180))))) -> 2950 | J35: ='Pricing & Assumptions'!$B$9 -> 1180 | K35: =G35*I35 -> 177000 | L35: =G35*J35 -> 70800 | M35: =K35-L35 -> 106200 | N35: =M35*5 -> 531000 | O35: =G35*('Pricing & Assumptions'!$B$3-'Pricing & Assumptions'!$B$9)*5 -> 354000 | P35: Indicative planning estimate; replace with official headcount when available
A36: 35 | B36: Dubai Judicial Institute | D36: 150 | E36: Planning estimate – validate with entity | F36: 0.7 | G36: =ROUND(D36*F36,0) -> 105 | I36: =IF(G36<100,2950,IF(G36<500,2213,IF(G36<1000,2065,IF(G36<2000,1770,IF(G36<3000,1475,1180))))) -> 2213 | J36: ='Pricing & Assumptions'!$B$9 -> 1180 | K36: =G36*I36 -> 232365 | L36: =G36*J36 -> 123900 | M36: =K36-L36 -> 108465 | N36: =M36*5 -> 542325 | O36: =G36*('Pricing & Assumptions'!$B$3-'Pricing & Assumptions'!$B$9)*5 -> 619500 | P36: Indicative planning estimate; replace with official headcount when available
A37: 36 | B37: Dubai Land Department (DLD) | C37: Important | D37: 1000 | E37: Planning estimate – validate with entity | F37: 0.7 | G37: =ROUND(D37*F37,0) -> 700 | I37: =IF(G37<100,2950,IF(G37<500,2213,IF(G37<1000,2065,IF(G37<2000,1770,IF(G37<3000,1475,1180))))) -> 2065 | J37: ='Pricing & Assumptions'!$B$9 -> 1180 | K37: =G37*I37 -> 1445500 | L37: =G37*J37 -> 826000 | M37: =K37-L37 -> 619500 | N37: =M37*5 -> 3097500 | O37: =G37*('Pricing & Assumptions'!$B$3-'Pricing & Assumptions'!$B$9)*5 -> 4130000 | P37: Indicative planning estimate; replace with official headcount when available
A38: 37 | B38: Dubai Maritime City Authority | D38: 250 | E38: Planning estimate – validate with entity | F38: 0.5 | G38: =ROUND(D38*F38,0) -> 125 | I38: =IF(G38<100,2950,IF(G38<500,2213,IF(G38<1000,2065,IF(G38<2000,1770,IF(G38<3000,1475,1180))))) -> 2213 | J38: ='Pricing & Assumptions'!$B$9 -> 1180 | K38: =G38*I38 -> 276625 | L38: =G38*J38 -> 147500 | M38: =K38-L38 -> 129125 | N38: =M38*5 -> 645625 | O38: =G38*('Pricing & Assumptions'!$B$3-'Pricing & Assumptions'!$B$9)*5 -> 737500 | P38: Indicative planning estimate; replace with official headcount when available
A39: 38 | B39: Dubai Media Council | D39: 200 | E39: Planning estimate – validate with entity | F39: 0.7 | G39: =ROUND(D39*F39,0) -> 140 | I39: =IF(G39<100,2950,IF(G39<500,2213,IF(G39<1000,2065,IF(G39<2000,1770,IF(G39<3000,1475,1180))))) -> 2213 | J39: ='Pricing & Assumptions'!$B$9 -> 1180 | K39: =G39*I39 -> 309820 | L39: =G39*J39 -> 165200 | M39: =K39-L39 -> 144620 | N39: =M39*5 -> 723100 | O39: =G39*('Pricing & Assumptions'!$B$3-'Pricing & Assumptions'!$B$9)*5 -> 826000 | P39: Indicative planning estimate; replace with official headcount when available
A40: 39 | B40: Dubai Media Inc | D40: 2500 | E40: Planning estimate – validate with entity | F40: 0.5 | G40: =ROUND(D40*F40,0) -> 1250 | I40: =IF(G40<100,2950,IF(G40<500,2213,IF(G40<1000,2065,IF(G40<2000,1770,IF(G40<3000,1475,1180))))) -> 1770 | J40: ='Pricing & Assumptions'!$B$9 -> 1180 | K40: =G40*I40 -> 2212500 | L40: =G40*J40 -> 1475000 | M40: =K40-L40 -> 737500 | N40: =M40*5 -> 3687500 | O40: =G40*('Pricing & Assumptions'!$B$3-'Pricing & Assumptions'!$B$9)*5 -> 7375000 | P40: Indicative planning estimate; replace with official headcount when available
A41: 40 | B41: Dubai Municipality | C41: In progress | D41: 11000 | E41: Public company profile | F41: 0.3 | G41: =ROUND(D41*F41,0) -> 3300 | I41: =IF(G41<100,2950,IF(G41<500,2213,IF(G41<1000,2065,IF(G41<2000,1770,IF(G41<3000,1475,1180))))) -> 1180 | J41: ='Pricing & Assumptions'!$B$9 -> 1180 | K41: =G41*I41 -> 3894000 | L41: =G41*J41 -> 3894000 | M41: =K41-L41 -> 0 | N41: =M41*5 -> 0 | O41: =G41*('Pricing & Assumptions'!$B$3-'Pricing & Assumptions'!$B$9)*5 -> 19470000 | P41: https://www.linkedin.com/company/dubai-municipality/
A42: 41 | B42: Dubai Petroleum | C42: DocuSign | D42: 1000 | E42: Planning estimate – validate with entity | F42: 0.5 | G42: =ROUND(D42*F42,0) -> 500 | I42: =IF(G42<100,2950,IF(G42<500,2213,IF(G42<1000,2065,IF(G42<2000,1770,IF(G42<3000,1475,1180))))) -> 2065 | J42: ='Pricing & Assumptions'!$B$9 -> 1180 | K42: =G42*I42 -> 1032500 | L42: =G42*J42 -> 590000 | M42: =K42-L42 -> 442500 | N42: =M42*5 -> 2212500 | O42: =G42*('Pricing & Assumptions'!$B$3-'Pricing & Assumptions'!$B$9)*5 -> 2950000 | P42: Indicative planning estimate; replace with official headcount when available
A43: 42 | B43: Dubai Police | D43: 22000 | E43: Public profile / approximate | F43: 0.3 | G43: =ROUND(D43*F43,0) -> 6600 | I43: =IF(G43<100,2950,IF(G43<500,2213,IF(G43<1000,2065,IF(G43<2000,1770,IF(G43<3000,1475,1180))))) -> 1180 | J43: ='Pricing & Assumptions'!$B$9 -> 1180 | K43: =G43*I43 -> 7788000 | L43: =G43*J43 -> 7788000 | M43: =K43-L43 -> 0 | N43: =M43*5 -> 0 | O43: =G43*('Pricing & Assumptions'!$B$3-'Pricing & Assumptions'!$B$9)*5 -> 38940000 | P43: https://ae.linkedin.com/company/dubaipolicehq
A44: 43 | B44: Dubai Public Prosecution | D44: 1000 | E44: Planning estimate – validate with entity | F44: 0.5 | G44: =ROUND(D44*F44,0) -> 500 | I44: =IF(G44<100,2950,IF(G44<500,2213,IF(G44<1000,2065,IF(G44<2000,1770,IF(G44<3000,1475,1180))))) -> 2065 | J44: ='Pricing & Assumptions'!$B$9 -> 1180 | K44: =G44*I44 -> 1032500 | L44: =G44*J44 -> 590000 | M44: =K44-L44 -> 442500 | N44: =M44*5 -> 2212500 | O44: =G44*('Pricing & Assumptions'!$B$3-'Pricing & Assumptions'!$B$9)*5 -> 2950000 | P44: Indicative planning estimate; replace with official headcount when available
A45: 44 | B45: Dubai Silicon Oasis Authority | D45: 600 | E45: Planning estimate – validate with entity | F45: 0.5 | G45: =ROUND(D45*F45,0) -> 300 | I45: =IF(G45<100,2950,IF(G45<500,2213,IF(G45<1000,2065,IF(G45<2000,1770,IF(G45<3000,1475,1180))))) -> 2213 | J45: ='Pricing & Assumptions'!$B$9 -> 1180 | K45: =G45*I45 -> 663900 | L45: =G45*J45 -> 354000 | M45: =K45-L45 -> 309900 | N45: =M45*5 -> 1549500 | O45: =G45*('Pricing & Assumptions'!$B$3-'Pricing & Assumptions'!$B$9)*5 -> 1770000 | P45: Indicative planning estimate; replace with official headcount when available
A46: 45 | B46: Dubai South | C46: DocuSign | D46: 1500 | E46: Planning estimate – validate with entity | F46: 0.3 | G46: =ROUND(D46*F46,0) -> 450 | I46: =IF(G46<100,2950,IF(G46<500,2213,IF(G46<1000,2065,IF(G46<2000,1770,IF(G46<3000,1475,1180))))) -> 2213 | J46: ='Pricing & Assumptions'!$B$9 -> 1180 | K46: =G46*I46 -> 995850 | L46: =G46*J46 -> 531000 | M46: =K46-L46 -> 464850 | N46: =M46*5 -> 2324250 | O46: =G46*('Pricing & Assumptions'!$B$3-'Pricing & Assumptions'!$B$9)*5 -> 2655000 | P46: Indicative planning estimate; replace with official headcount when available
A47: 46 | B47: Dubai Sports Council | D47: 250 | E47: Planning estimate – validate with entity | F47: 0.5 | G47: =ROUND(D47*F47,0) -> 125 | I47: =IF(G47<100,2950,IF(G47<500,2213,IF(G47<1000,2065,IF(G47<2000,1770,IF(G47<3000,1475,1180))))) -> 2213 | J47: ='Pricing & Assumptions'!$B$9 -> 1180 | K47: =G47*I47 -> 276625 | L47: =G47*J47 -> 147500 | M47: =K47-L47 -> 129125 | N47: =M47*5 -> 645625 | O47: =G47*('Pricing & Assumptions'!$B$3-'Pricing & Assumptions'!$B$9)*5 -> 737500 | P47: Indicative planning estimate; replace with official headcount when available
A48: 47 | B48: Dubai Statistics Center | D48: 350 | E48: Planning estimate – validate with entity | F48: 0.7 | G48: =ROUND(D48*F48,0) -> 245 | I48: =IF(G48<100,2950,IF(G48<500,2213,IF(G48<1000,2065,IF(G48<2000,1770,IF(G48<3000,1475,1180))))) -> 2213 | J48: ='Pricing & Assumptions'!$B$9 -> 1180 | K48: =G48*I48 -> 542185 | L48: =G48*J48 -> 289100 | M48: =K48-L48 -> 253085 | N48: =M48*5 -> 1265425 | O48: =G48*('Pricing & Assumptions'!$B$3-'Pricing & Assumptions'!$B$9)*5 -> 1445500 | P48: Indicative planning estimate; replace with official headcount when available
A49: 48 | B49: Dubai Municipality | C49: In progress | D49: 11000 | E49: Public company profile | F49: 0.3 | G49: =ROUND(D49*F49,0) -> 3300 | I49: =IF(G49<100,2950,IF(G49<500,2213,IF(G49<1000,2065,IF(G49<2000,1770,IF(G49<3000,1475,1180))))) -> 1180 | J49: ='Pricing & Assumptions'!$B$9 -> 1180 | K49: =G49*I49 -> 3894000 | L49: =G49*J49 -> 3894000 | M49: =K49-L49 -> 0 | N49: =M49*5 -> 0 | O49: =G49*('Pricing & Assumptions'!$B$3-'Pricing & Assumptions'!$B$9)*5 -> 19470000 | P49: https://www.linkedin.com/company/dubai-municipality/
A50: 49 | B50: Dubai Women Establishment | D50: 150 | E50: Planning estimate – validate with entity | F50: 0.5 | G50: =ROUND(D50*F50,0) -> 75 | I50: =IF(G50<100,2950,IF(G50<500,2213,IF(G50<1000,2065,IF(G50<2000,1770,IF(G50<3000,1475,1180))))) -> 2950 | J50: ='Pricing & Assumptions'!$B$9 -> 1180 | K50: =G50*I50 -> 221250 | L50: =G50*J50 -> 88500 | M50: =K50-L50 -> 132750 | N50: =M50*5 -> 663750 | O50: =G50*('Pricing & Assumptions'!$B$3-'Pricing & Assumptions'!$B$9)*5 -> 442500 | P50: Indicative planning estimate; replace with official headcount when available
A51: 50 | B51: Economic Security Center of Dubai | D51: 200 | E51: Planning estimate – validate with entity | F51: 0.7 | G51: =ROUND(D51*F51,0) -> 140 | I51: =IF(G51<100,2950,IF(G51<500,2213,IF(G51<1000,2065,IF(G51<2000,1770,IF(G51<3000,1475,1180))))) -> 2213 | J51: ='Pricing & Assumptions'!$B$9 -> 1180 | K51: =G51*I51 -> 309820 | L51: =G51*J51 -> 165200 | M51: =K51-L51 -> 144620 | N51: =M51*5 -> 723100 | O51: =G51*('Pricing & Assumptions'!$B$3-'Pricing & Assumptions'!$B$9)*5 -> 826000 | P51: Indicative planning estimate; replace with official headcount when available
A52: 51 | B52: Emirates International Accreditation Centre (eiac) | D52: 150 | E52: Planning estimate – validate with entity | F52: 0.5 | G52: =ROUND(D52*F52,0) -> 75 | I52: =IF(G52<100,2950,IF(G52<500,2213,IF(G52<1000,2065,IF(G52<2000,1770,IF(G52<3000,1475,1180))))) -> 2950 | J52: ='Pricing & Assumptions'!$B$9 -> 1180 | K52: =G52*I52 -> 221250 | L52: =G52*J52 -> 88500 | M52: =K52-L52 -> 132750 | N52: =M52*5 -> 663750 | O52: =G52*('Pricing & Assumptions'!$B$3-'Pricing & Assumptions'!$B$9)*5 -> 442500 | P52: Indicative planning estimate; replace with official headcount when available
A53: 52 | B53: Endowment And Minor Trust Foundation | D53: 600 | E53: Planning estimate – validate with entity | F53: 0.5 | G53: =ROUND(D53*F53,0) -> 300 | I53: =IF(G53<100,2950,IF(G53<500,2213,IF(G53<1000,2065,IF(G53<2000,1770,IF(G53<3000,1475,1180))))) -> 2213 | J53: ='Pricing & Assumptions'!$B$9 -> 1180 | K53: =G53*I53 -> 663900 | L53: =G53*J53 -> 354000 | M53: =K53-L53 -> 309900 | N53: =M53*5 -> 1549500 | O53: =G53*('Pricing & Assumptions'!$B$3-'Pricing & Assumptions'!$B$9)*5 -> 1770000 | P53: Indicative planning estimate; replace with official headcount when available
A54: 53 | B54: Financial Audit Authority | C54: AdobeSign | D54: 500 | E54: Planning estimate – validate with entity | F54: 0.7 | G54: =ROUND(D54*F54,0) -> 350 | I54: =IF(G54<100,2950,IF(G54<500,2213,IF(G54<1000,2065,IF(G54<2000,1770,IF(G54<3000,1475,1180))))) -> 2213 | J54: ='Pricing & Assumptions'!$B$9 -> 1180 | K54: =G54*I54 -> 774550 | L54: =G54*J54 -> 413000 | M54: =K54-L54 -> 361550 | N54: =M54*5 -> 1807750 | O54: =G54*('Pricing & Assumptions'!$B$3-'Pricing & Assumptions'!$B$9)*5 -> 2065000 | P54: Indicative planning estimate; replace with official headcount when available
A55: 54 | B55: General Directorate of Residency and Forigners Affairs - Dubai | D55: 8000 | E55: Planning estimate – validate with entity | F55: 0.3 | G55: =ROUND(D55*F55,0) -> 2400 | I55: =IF(G55<100,2950,IF(G55<500,2213,IF(G55<1000,2065,IF(G55<2000,1770,IF(G55<3000,1475,1180))))) -> 1475 | J55: ='Pricing & Assumptions'!$B$9 -> 1180 | K55: =G55*I55 -> 3540000 | L55: =G55*J55 -> 2832000 | M55: =K55-L55 -> 708000 | N55: =M55*5 -> 3540000 | O55: =G55*('Pricing & Assumptions'!$B$3-'Pricing & Assumptions'!$B$9)*5 -> 14160000 | P55: Indicative planning estimate; replace with official headcount when available
A56: 55 | B56: Hamdan Bin Mohammed Smart University | D56: 500 | E56: Planning estimate – validate with entity | F56: 0.5 | G56: =ROUND(D56*F56,0) -> 250 | I56: =IF(G56<100,2950,IF(G56<500,2213,IF(G56<1000,2065,IF(G56<2000,1770,IF(G56<3000,1475,1180))))) -> 2213 | J56: ='Pricing & Assumptions'!$B$9 -> 1180 | K56: =G56*I56 -> 553250 | L56: =G56*J56 -> 295000 | M56: =K56-L56 -> 258250 | N56: =M56*5 -> 1291250 | O56: =G56*('Pricing & Assumptions'!$B$3-'Pricing & Assumptions'!$B$9)*5 -> 1475000 | P56: Indicative planning estimate; replace with official headcount when available
A57: 56 | B57: International City for Humanitarian Services | D57: 300 | E57: Planning estimate – validate with entity | F57: 0.5 | G57: =ROUND(D57*F57,0) -> 150 | I57: =IF(G57<100,2950,IF(G57<500,2213,IF(G57<1000,2065,IF(G57<2000,1770,IF(G57<3000,1475,1180))))) -> 2213 | J57: ='Pricing & Assumptions'!$B$9 -> 1180 | K57: =G57*I57 -> 331950 | L57: =G57*J57 -> 177000 | M57: =K57-L57 -> 154950 | N57: =M57*5 -> 774750 | O57: =G57*('Pricing & Assumptions'!$B$3-'Pricing & Assumptions'!$B$9)*5 -> 885000 | P57: Indicative planning estimate; replace with official headcount when available
A58: 57 | B58: Investment Corporation of Dubai | C58: Customer | D58: 250 | E58: Planning estimate – validate with entity | F58: 0.5 | G58: =ROUND(D58*F58,0) -> 125 | H58: 150 | I58: =IF(G58<100,2950,IF(G58<500,2213,IF(G58<1000,2065,IF(G58<2000,1770,IF(G58<3000,1475,1180))))) -> 2213 | J58: ='Pricing & Assumptions'!$B$9 -> 1180 | K58: =G58*I58 -> 276625 | L58: =G58*J58 -> 147500 | M58: =K58-L58 -> 129125 | N58: =M58*5 -> 645625 | O58: =G58*('Pricing & Assumptions'!$B$3-'Pricing & Assumptions'!$B$9)*5 -> 737500 | P58: Indicative planning estimate; replace with official headcount when available
A59: 58 | B59: Islamic Affairs & Charitable Activities Department (Awqaf Dubai) | D59: 1200 | E59: Planning estimate – validate with entity | F59: 0.5 | G59: =ROUND(D59*F59,0) -> 600 | I59: =IF(G59<100,2950,IF(G59<500,2213,IF(G59<1000,2065,IF(G59<2000,1770,IF(G59<3000,1475,1180))))) -> 2065 | J59: ='Pricing & Assumptions'!$B$9 -> 1180 | K59: =G59*I59 -> 1239000 | L59: =G59*J59 -> 708000 | M59: =K59-L59 -> 531000 | N59: =M59*5 -> 2655000 | O59: =G59*('Pricing & Assumptions'!$B$3-'Pricing & Assumptions'!$B$9)*5 -> 3540000 | P59: Indicative planning estimate; replace with official headcount when available
A60: 59 | B60: Jabel Ali Free Zone | D60: 1200 | E60: Planning estimate – validate with entity | F60: 0.3 | G60: =ROUND(D60*F60,0) -> 360 | I60: =IF(G60<100,2950,IF(G60<500,2213,IF(G60<1000,2065,IF(G60<2000,1770,IF(G60<3000,1475,1180))))) -> 2213 | J60: ='Pricing & Assumptions'!$B$9 -> 1180 | K60: =G60*I60 -> 796680 | L60: =G60*J60 -> 424800 | M60: =K60-L60 -> 371880 | N60: =M60*5 -> 1859400 | O60: =G60*('Pricing & Assumptions'!$B$3-'Pricing & Assumptions'!$B$9)*5 -> 2124000 | P60: Indicative planning estimate; replace with official headcount when available
A61: 60 | B61: Khbrati | D61: 100 | E61: Planning estimate – validate with entity | F61: 0.5 | G61: =ROUND(D61*F61,0) -> 50 | I61: =IF(G61<100,2950,IF(G61<500,2213,IF(G61<1000,2065,IF(G61<2000,1770,IF(G61<3000,1475,1180))))) -> 2950 | J61: ='Pricing & Assumptions'!$B$9 -> 1180 | K61: =G61*I61 -> 147500 | L61: =G61*J61 -> 59000 | M61: =K61-L61 -> 88500 | N61: =M61*5 -> 442500 | O61: =G61*('Pricing & Assumptions'!$B$3-'Pricing & Assumptions'!$B$9)*5 -> 295000 | P61: Indicative planning estimate; replace with official headcount when available
A62: 61 | B62: Knowledge and Human Development Authority | D62: 500 | E62: Planning estimate – validate with entity | F62: 0.7 | G62: =ROUND(D62*F62,0) -> 350 | I62: =IF(G62<100,2950,IF(G62<500,2213,IF(G62<1000,2065,IF(G62<2000,1770,IF(G62<3000,1475,1180))))) -> 2213 | J62: ='Pricing & Assumptions'!$B$9 -> 1180 | K62: =G62*I62 -> 774550 | L62: =G62*J62 -> 413000 | M62: =K62-L62 -> 361550 | N62: =M62*5 -> 1807750 | O62: =G62*('Pricing & Assumptions'!$B$3-'Pricing & Assumptions'!$B$9)*5 -> 2065000 | P62: Indicative planning estimate; replace with official headcount when available
A63: 62 | B63: Knowledge Fund Foundation | D63: 100 | E63: Planning estimate – validate with entity | F63: 0.7 | G63: =ROUND(D63*F63,0) -> 70 | I63: =IF(G63<100,2950,IF(G63<500,2213,IF(G63<1000,2065,IF(G63<2000,1770,IF(G63<3000,1475,1180))))) -> 2950 | J63: ='Pricing & Assumptions'!$B$9 -> 1180 | K63: =G63*I63 -> 206500 | L63: =G63*J63 -> 82600 | M63: =K63-L63 -> 123900 | N63: =M63*5 -> 619500 | O63: =G63*('Pricing & Assumptions'!$B$3-'Pricing & Assumptions'!$B$9)*5 -> 413000 | P63: Indicative planning estimate; replace with official headcount when available
A64: 63 | B64: Mohamed Bin Rashid Space Centre | D64: 700 | E64: Planning estimate – validate with entity | F64: 0.5 | G64: =ROUND(D64*F64,0) -> 350 | I64: =IF(G64<100,2950,IF(G64<500,2213,IF(G64<1000,2065,IF(G64<2000,1770,IF(G64<3000,1475,1180))))) -> 2213 | J64: ='Pricing & Assumptions'!$B$9 -> 1180 | K64: =G64*I64 -> 774550 | L64: =G64*J64 -> 413000 | M64: =K64-L64 -> 361550 | N64: =M64*5 -> 1807750 | O64: =G64*('Pricing & Assumptions'!$B$3-'Pricing & Assumptions'!$B$9)*5 -> 2065000 | P64: Indicative planning estimate; replace with official headcount when available
A65: 64 | B65: Mohammed Bin Rashid Al Maktoum Knowledge Foundation | D65: 200 | E65: Planning estimate – validate with entity | F65: 0.7 | G65: =ROUND(D65*F65,0) -> 140 | I65: =IF(G65<100,2950,IF(G65<500,2213,IF(G65<1000,2065,IF(G65<2000,1770,IF(G65<3000,1475,1180))))) -> 2213 | J65: ='Pricing & Assumptions'!$B$9 -> 1180 | K65: =G65*I65 -> 309820 | L65: =G65*J65 -> 165200 | M65: =K65-L65 -> 144620 | N65: =M65*5 -> 723100 | O65: =G65*('Pricing & Assumptions'!$B$3-'Pricing & Assumptions'!$B$9)*5 -> 826000 | P65: Indicative planning estimate; replace with official headcount when available
A66: 65 | B66: Mohammed Bin Rashid Al Maktoum Library Foundation | D66: 300 | E66: Planning estimate – validate with entity | F66: 0.5 | G66: =ROUND(D66*F66,0) -> 150 | I66: =IF(G66<100,2950,IF(G66<500,2213,IF(G66<1000,2065,IF(G66<2000,1770,IF(G66<3000,1475,1180))))) -> 2213 | J66: ='Pricing & Assumptions'!$B$9 -> 1180 | K66: =G66*I66 -> 331950 | L66: =G66*J66 -> 177000 | M66: =K66-L66 -> 154950 | N66: =M66*5 -> 774750 | O66: =G66*('Pricing & Assumptions'!$B$3-'Pricing & Assumptions'!$B$9)*5 -> 885000 | P66: Indicative planning estimate; replace with official headcount when available
A67: 66 | B67: Mohammed Bin Rashid Housing Establishment | C67: In progress | D67: 800 | E67: Planning estimate – validate with entity | F67: 0.5 | G67: =ROUND(D67*F67,0) -> 400 | I67: =IF(G67<100,2950,IF(G67<500,2213,IF(G67<1000,2065,IF(G67<2000,1770,IF(G67<3000,1475,1180))))) -> 2213 | J67: ='Pricing & Assumptions'!$B$9 -> 1180 | K67: =G67*I67 -> 885200 | L67: =G67*J67 -> 472000 | M67: =K67-L67 -> 413200 | N67: =M67*5 -> 2066000 | O67: =G67*('Pricing & Assumptions'!$B$3-'Pricing & Assumptions'!$B$9)*5 -> 2360000 | P67: Indicative planning estimate; replace with official headcount when available
A68: 67 | B68: Mohammed Bin Rashid School of Government | D68: 250 | E68: Planning estimate – validate with entity | F68: 0.7 | G68: =ROUND(D68*F68,0) -> 175 | I68: =IF(G68<100,2950,IF(G68<500,2213,IF(G68<1000,2065,IF(G68<2000,1770,IF(G68<3000,1475,1180))))) -> 2213 | J68: ='Pricing & Assumptions'!$B$9 -> 1180 | K68: =G68*I68 -> 387275 | L68: =G68*J68 -> 206500 | M68: =K68-L68 -> 180775 | N68: =M68*5 -> 903875 | O68: =G68*('Pricing & Assumptions'!$B$3-'Pricing & Assumptions'!$B$9)*5 -> 1032500 | P68: Indicative planning estimate; replace with official headcount when available
A69: 68 | B69: National Bonds | D69: 500 | E69: Planning estimate – validate with entity | F69: 0.5 | G69: =ROUND(D69*F69,0) -> 250 | I69: =IF(G69<100,2950,IF(G69<500,2213,IF(G69<1000,2065,IF(G69<2000,1770,IF(G69<3000,1475,1180))))) -> 2213 | J69: ='Pricing & Assumptions'!$B$9 -> 1180 | K69: =G69*I69 -> 553250 | L69: =G69*J69 -> 295000 | M69: =K69-L69 -> 258250 | N69: =M69*5 -> 1291250 | O69: =G69*('Pricing & Assumptions'!$B$3-'Pricing & Assumptions'!$B$9)*5 -> 1475000 | P69: Indicative planning estimate; replace with official headcount when available
A70: 69 | B70: Nedaa - Professional Communication Corporation | D70: 400 | E70: Planning estimate – validate with entity | F70: 0.5 | G70: =ROUND(D70*F70,0) -> 200 | I70: =IF(G70<100,2950,IF(G70<500,2213,IF(G70<1000,2065,IF(G70<2000,1770,IF(G70<3000,1475,1180))))) -> 2213 | J70: ='Pricing & Assumptions'!$B$9 -> 1180 | K70: =G70*I70 -> 442600 | L70: =G70*J70 -> 236000 | M70: =K70-L70 -> 206600 | N70: =M70*5 -> 1033000 | O70: =G70*('Pricing & Assumptions'!$B$3-'Pricing & Assumptions'!$B$9)*5 -> 1180000 | P70: Indicative planning estimate; replace with official headcount when available
A71: 70 | B71: Ports, Customs and Free Zone Corporation (PCFC) | C71: Customer | D71: 1500 | E71: Planning estimate – validate with entity | F71: 0.5 | G71: =ROUND(D71*F71,0) -> 750 | H71: 30 | I71: =IF(G71<100,2950,IF(G71<500,2213,IF(G71<1000,2065,IF(G71<2000,1770,IF(G71<3000,1475,1180))))) -> 2065 | J71: ='Pricing & Assumptions'!$B$9 -> 1180 | K71: =G71*I71 -> 1548750 | L71: =G71*J71 -> 885000 | M71: =K71-L71 -> 663750 | N71: =M71*5 -> 3318750 | O71: =G71*('Pricing & Assumptions'!$B$3-'Pricing & Assumptions'!$B$9)*5 -> 4425000 | P71: Indicative planning estimate; replace with official headcount when available
A72: 71 | B72: Professional Communication Corporation 'Nedaa' | D72: 400 | E72: Planning estimate – validate with entity | F72: 0.5 | G72: =ROUND(D72*F72,0) -> 200 | I72: =IF(G72<100,2950,IF(G72<500,2213,IF(G72<1000,2065,IF(G72<2000,1770,IF(G72<3000,1475,1180))))) -> 2213 | J72: ='Pricing & Assumptions'!$B$9 -> 1180 | K72: =G72*I72 -> 442600 | L72: =G72*J72 -> 236000 | M72: =K72-L72 -> 206600 | N72: =M72*5 -> 1033000 | O72: =G72*('Pricing & Assumptions'!$B$3-'Pricing & Assumptions'!$B$9)*5 -> 1180000 | P72: Indicative planning estimate; replace with official headcount when available
A73: 72 | B73: Protocol Department | D73: 300 | E73: Planning estimate – validate with entity | F73: 0.5 | G73: =ROUND(D73*F73,0) -> 150 | I73: =IF(G73<100,2950,IF(G73<500,2213,IF(G73<1000,2065,IF(G73<2000,1770,IF(G73<3000,1475,1180))))) -> 2213 | J73: ='Pricing & Assumptions'!$B$9 -> 1180 | K73: =G73*I73 -> 331950 | L73: =G73*J73 -> 177000 | M73: =K73-L73 -> 154950 | N73: =M73*5 -> 774750 | O73: =G73*('Pricing & Assumptions'!$B$3-'Pricing & Assumptions'!$B$9)*5 -> 885000 | P73: Indicative planning estimate; replace with official headcount when available
A74: 73 | B74: Public Prosecution | D74: 1000 | E74: Planning estimate – validate with entity | F74: 0.5 | G74: =ROUND(D74*F74,0) -> 500 | I74: =IF(G74<100,2950,IF(G74<500,2213,IF(G74<1000,2065,IF(G74<2000,1770,IF(G74<3000,1475,1180))))) -> 2065 | J74: ='Pricing & Assumptions'!$B$9 -> 1180 | K74: =G74*I74 -> 1032500 | L74: =G74*J74 -> 590000 | M74: =K74-L74 -> 442500 | N74: =M74*5 -> 2212500 | O74: =G74*('Pricing & Assumptions'!$B$3-'Pricing & Assumptions'!$B$9)*5 -> 2950000 | P74: Indicative planning estimate; replace with official headcount when available
A75: 74 | B75: Roads and Transport Authority (RTA) | C75: Customer | D75: 5015 | E75: Published 2023 | F75: 0.5 | G75: =ROUND(D75*F75,0) -> 2508 | H75: 1000 | I75: =IF(G75<100,2950,IF(G75<500,2213,IF(G75<1000,2065,IF(G75<2000,1770,IF(G75<3000,1475,1180))))) -> 1475 | J75: ='Pricing & Assumptions'!$B$9 -> 1180 | K75: =G75*I75 -> 3699300 | L75: =G75*J75 -> 2959440 | M75: =K75-L75 -> 739860 | N75: =M75*5 -> 3699300 | O75: =G75*('Pricing & Assumptions'!$B$3-'Pricing & Assumptions'!$B$9)*5 -> 14797200 | P75: https://www.rta.ae/wps/portal/rta/ae/home/news-and-media/all-news/NewsDetails/women-committee-celebrates-emirati-women-day
A76: 75 | B76: Security Industry Regulatory Authority | D76: 700 | E76: Planning estimate – validate with entity | F76: 0.5 | G76: =ROUND(D76*F76,0) -> 350 | I76: =IF(G76<100,2950,IF(G76<500,2213,IF(G76<1000,2065,IF(G76<2000,1770,IF(G76<3000,1475,1180))))) -> 2213 | J76: ='Pricing & Assumptions'!$B$9 -> 1180 | K76: =G76*I76 -> 774550 | L76: =G76*J76 -> 413000 | M76: =K76-L76 -> 361550 | N76: =M76*5 -> 1807750 | O76: =G76*('Pricing & Assumptions'!$B$3-'Pricing & Assumptions'!$B$9)*5 -> 2065000 | P76: Indicative planning estimate; replace with official headcount when available
A77: 76 | B77: State Security - Dubai | D77: 4000 | E77: Planning estimate – validate with entity | F77: 0.3 | G77: =ROUND(D77*F77,0) -> 1200 | I77: =IF(G77<100,2950,IF(G77<500,2213,IF(G77<1000,2065,IF(G77<2000,1770,IF(G77<3000,1475,1180))))) -> 1770 | J77: ='Pricing & Assumptions'!$B$9 -> 1180 | K77: =G77*I77 -> 2124000 | L77: =G77*J77 -> 1416000 | M77: =K77-L77 -> 708000 | N77: =M77*5 -> 3540000 | O77: =G77*('Pricing & Assumptions'!$B$3-'Pricing & Assumptions'!$B$9)*5 -> 7080000 | P77: Indicative planning estimate; replace with official headcount when available
A78: 77 | B78: Supreme Council of Energy Dubai | D78: 100 | E78: Planning estimate – validate with entity | F78: 0.5 | G78: =ROUND(D78*F78,0) -> 50 | I78: =IF(G78<100,2950,IF(G78<500,2213,IF(G78<1000,2065,IF(G78<2000,1770,IF(G78<3000,1475,1180))))) -> 2950 | J78: ='Pricing & Assumptions'!$B$9 -> 1180 | K78: =G78*I78 -> 147500 | L78: =G78*J78 -> 59000 | M78: =K78-L78 -> 88500 | N78: =M78*5 -> 442500 | O78: =G78*('Pricing & Assumptions'!$B$3-'Pricing & Assumptions'!$B$9)*5 -> 295000 | P78: Indicative planning estimate; replace with official headcount when available
A79: 78 | B79: Supreme Legislation Committee | C79: In progress | D79: 250 | E79: Planning estimate – validate with entity | F79: 0.7 | G79: =ROUND(D79*F79,0) -> 175 | I79: =IF(G79<100,2950,IF(G79<500,2213,IF(G79<1000,2065,IF(G79<2000,1770,IF(G79<3000,1475,1180))))) -> 2213 | J79: ='Pricing & Assumptions'!$B$9 -> 1180 | K79: =G79*I79 -> 387275 | L79: =G79*J79 -> 206500 | M79: =K79-L79 -> 180775 | N79: =M79*5 -> 903875 | O79: =G79*('Pricing & Assumptions'!$B$3-'Pricing & Assumptions'!$B$9)*5 -> 1032500 | P79: Indicative planning estimate; replace with official headcount when available
A80: 79 | B80: The Executive Council - Dubai | C80: AdobeSign | D80: 300 | E80: Planning estimate – validate with entity | F80: 0.7 | G80: =ROUND(D80*F80,0) -> 210 | I80: =IF(G80<100,2950,IF(G80<500,2213,IF(G80<1000,2065,IF(G80<2000,1770,IF(G80<3000,1475,1180))))) -> 2213 | J80: ='Pricing & Assumptions'!$B$9 -> 1180 | K80: =G80*I80 -> 464730 | L80: =G80*J80 -> 247800 | M80: =K80-L80 -> 216930 | N80: =M80*5 -> 1084650 | O80: =G80*('Pricing & Assumptions'!$B$3-'Pricing & Assumptions'!$B$9)*5 -> 1239000 | P80: Indicative planning estimate; replace with official headcount when available
A81: 80 | B81: The Governement of Dubai Human Resources Department | D81: 400 | E81: Planning estimate – validate with entity | F81: 0.7 | G81: =ROUND(D81*F81,0) -> 280 | I81: =IF(G81<100,2950,IF(G81<500,2213,IF(G81<1000,2065,IF(G81<2000,1770,IF(G81<3000,1475,1180))))) -> 2213 | J81: ='Pricing & Assumptions'!$B$9 -> 1180 | K81: =G81*I81 -> 619640 | L81: =G81*J81 -> 330400 | M81: =K81-L81 -> 289240 | N81: =M81*5 -> 1446200 | O81: =G81*('Pricing & Assumptions'!$B$3-'Pricing & Assumptions'!$B$9)*5 -> 1652000 | P81: Indicative planning estimate; replace with official headcount when available
A82: 81 | B82: The Government of Dubai Legal Affairs Department | D82: 350 | E82: Planning estimate – validate with entity | F82: 0.7 | G82: =ROUND(D82*F82,0) -> 245 | I82: =IF(G82<100,2950,IF(G82<500,2213,IF(G82<1000,2065,IF(G82<2000,1770,IF(G82<3000,1475,1180))))) -> 2213 | J82: ='Pricing & Assumptions'!$B$9 -> 1180 | K82: =G82*I82 -> 542185 | L82: =G82*J82 -> 289100 | M82: =K82-L82 -> 253085 | N82: =M82*5 -> 1265425 | O82: =G82*('Pricing & Assumptions'!$B$3-'Pricing & Assumptions'!$B$9)*5 -> 1445500 | P82: Indicative planning estimate; replace with official headcount when available
A83: 82 | B83: The Government of Dubai Media Office | D83: 350 | E83: Planning estimate – validate with entity | F83: 0.7 | G83: =ROUND(D83*F83,0) -> 245 | I83: =IF(G83<100,2950,IF(G83<500,2213,IF(G83<1000,2065,IF(G83<2000,1770,IF(G83<3000,1475,1180))))) -> 2213 | J83: ='Pricing & Assumptions'!$B$9 -> 1180 | K83: =G83*I83 -> 542185 | L83: =G83*J83 -> 289100 | M83: =K83-L83 -> 253085 | N83: =M83*5 -> 1265425 | O83: =G83*('Pricing & Assumptions'!$B$3-'Pricing & Assumptions'!$B$9)*5 -> 1445500 | P83: Indicative planning estimate; replace with official headcount when available
A84: 83 | B84: The Supreme Legislation Committee | D84: 250 | E84: Planning estimate – validate with entity | F84: 0.7 | G84: =ROUND(D84*F84,0) -> 175 | I84: =IF(G84<100,2950,IF(G84<500,2213,IF(G84<1000,2065,IF(G84<2000,1770,IF(G84<3000,1475,1180))))) -> 2213 | J84: ='Pricing & Assumptions'!$B$9 -> 1180 | K84: =G84*I84 -> 387275 | L84: =G84*J84 -> 206500 | M84: =K84-L84 -> 180775 | N84: =M84*5 -> 903875 | O84: =G84*('Pricing & Assumptions'!$B$3-'Pricing & Assumptions'!$B$9)*5 -> 1032500 | P84: Indicative planning estimate; replace with official headcount when available
A85: 84 | B85: Trakhees Corporation | D85: 700 | E85: Planning estimate – validate with entity | F85: 0.5 | G85: =ROUND(D85*F85,0) -> 350 | I85: =IF(G85<100,2950,IF(G85<500,2213,IF(G85<1000,2065,IF(G85<2000,1770,IF(G85<3000,1475,1180))))) -> 2213 | J85: ='Pricing & Assumptions'!$B$9 -> 1180 | K85: =G85*I85 -> 774550 | L85: =G85*J85 -> 413000 | M85: =K85-L85 -> 361550 | N85: =M85*5 -> 1807750 | O85: =G85*('Pricing & Assumptions'!$B$3-'Pricing & Assumptions'!$B$9)*5 -> 2065000 | P85: Indicative planning estimate; replace with official headcount when available
A86: 85 | B86: UAE Food Bank | D86: 100 | E86: Planning estimate – validate with entity | F86: 0.5 | G86: =ROUND(D86*F86,0) -> 50 | I86: =IF(G86<100,2950,IF(G86<500,2213,IF(G86<1000,2065,IF(G86<2000,1770,IF(G86<3000,1475,1180))))) -> 2950 | J86: ='Pricing & Assumptions'!$B$9 -> 1180 | K86: =G86*I86 -> 147500 | L86: =G86*J86 -> 59000 | M86: =K86-L86 -> 88500 | N86: =M86*5 -> 442500 | O86: =G86*('Pricing & Assumptions'!$B$3-'Pricing & Assumptions'!$B$9)*5 -> 295000 | P86: Indicative planning estimate; replace with official headcount when available
A87: 86 | B87: Visit Dubai | D87: 300 | E87: Planning estimate – validate with entity | F87: 0.5 | G87: =ROUND(D87*F87,0) -> 150 | I87: =IF(G87<100,2950,IF(G87<500,2213,IF(G87<1000,2065,IF(G87<2000,1770,IF(G87<3000,1475,1180))))) -> 2213 | J87: ='Pricing & Assumptions'!$B$9 -> 1180 | K87: =G87*I87 -> 331950 | L87: =G87*J87 -> 177000 | M87: =K87-L87 -> 154950 | N87: =M87*5 -> 774750 | O87: =G87*('Pricing & Assumptions'!$B$3-'Pricing & Assumptions'!$B$9)*5 -> 885000 | P87: Indicative planning estimate; replace with official headcount when available
A88: 87 | B88: Emirates Integrated Telecommunications Company (du) | D88: 3000 | E88: Planning estimate – validate with entity | F88: 0.5 | G88: =ROUND(D88*F88,0) -> 1500 | I88: =IF(G88<100,2950,IF(G88<500,2213,IF(G88<1000,2065,IF(G88<2000,1770,IF(G88<3000,1475,1180))))) -> 1770 | J88: ='Pricing & Assumptions'!$B$9 -> 1180 | K88: =G88*I88 -> 2655000 | L88: =G88*J88 -> 1770000 | M88: =K88-L88 -> 885000 | N88: =M88*5 -> 4425000 | O88: =G88*('Pricing & Assumptions'!$B$3-'Pricing & Assumptions'!$B$9)*5 -> 8850000 | P88: Indicative planning estimate; replace with official headcount when available
A89: 88 | B89: Mohammed Bin Rashid Al Maktoum Global Initiatives | D89: 500 | E89: Planning estimate – validate with entity | F89: 0.5 | G89: =ROUND(D89*F89,0) -> 250 | I89: =IF(G89<100,2950,IF(G89<500,2213,IF(G89<1000,2065,IF(G89<2000,1770,IF(G89<3000,1475,1180))))) -> 2213 | J89: ='Pricing & Assumptions'!$B$9 -> 1180 | K89: =G89*I89 -> 553250 | L89: =G89*J89 -> 295000 | M89: =K89-L89 -> 258250 | N89: =M89*5 -> 1291250 | O89: =G89*('Pricing & Assumptions'!$B$3-'Pricing & Assumptions'!$B$9)*5 -> 1475000 | P89: Indicative planning estimate; replace with official headcount when available
A90: 89 | B90: Mohammed Bin Rashid Centre for Government Innovation - Dubai | D90: 150 | E90: Planning estimate – validate with entity | F90: 0.5 | G90: =ROUND(D90*F90,0) -> 75 | I90: =IF(G90<100,2950,IF(G90<500,2213,IF(G90<1000,2065,IF(G90<2000,1770,IF(G90<3000,1475,1180))))) -> 2950 | J90: ='Pricing & Assumptions'!$B$9 -> 1180 | K90: =G90*I90 -> 221250 | L90: =G90*J90 -> 88500 | M90: =K90-L90 -> 132750 | N90: =M90*5 -> 663750 | O90: =G90*('Pricing & Assumptions'!$B$3-'Pricing & Assumptions'!$B$9)*5 -> 442500 | P90: Indicative planning estimate; replace with official headcount when available
A91: 90 | B91: Sheikh Zayed Housing Programme | D91: 800 | E91: Planning estimate – validate with entity | F91: 0.5 | G91: =ROUND(D91*F91,0) -> 400 | I91: =IF(G91<100,2950,IF(G91<500,2213,IF(G91<1000,2065,IF(G91<2000,1770,IF(G91<3000,1475,1180))))) -> 2213 | J91: ='Pricing & Assumptions'!$B$9 -> 1180 | K91: =G91*I91 -> 885200 | L91: =G91*J91 -> 472000 | M91: =K91-L91 -> 413200 | N91: =M91*5 -> 2066000 | O91: =G91*('Pricing & Assumptions'!$B$3-'Pricing & Assumptions'!$B$9)*5 -> 2360000 | P91: Indicative planning estimate; replace with official headcount when available
A92: 91 | B92: Dubai Healthcare City Authority | C92: Customer | D92: 500 | E92: Planning estimate – validate with entity | F92: 0.3 | G92: =ROUND(D92*F92,0) -> 150 | H92: 150 | I92: =IF(G92<100,2950,IF(G92<500,2213,IF(G92<1000,2065,IF(G92<2000,1770,IF(G92<3000,1475,1180))))) -> 2213 | J92: ='Pricing & Assumptions'!$B$9 -> 1180 | K92: =G92*I92 -> 331950 | L92: =G92*J92 -> 177000 | M92: =K92-L92 -> 154950 | N92: =M92*5 -> 774750 | O92: =G92*('Pricing & Assumptions'!$B$3-'Pricing & Assumptions'!$B$9)*5 -> 885000 | P92: Indicative planning estimate; replace with official headcount when available
B93: TOTAL / PORTFOLIO | D93: =SUM(D2:D92) -> 165227 | G93: =SUM(G2:G92) -> 61482 | H93: =SUM(H2:H92) -> 1840 | K93: =SUM(K2:K92) -> 102939175 | L93: =SUM(L2:L92) -> 72548760 | M93: =SUM(M2:M92) -> 30390415 | N93: =SUM(N2:N92) -> 151952075 | O93: =SUM(O2:O92) -> 362743800

Sheet Pricing & Assumptions
A1: Pricing / Model Assumption | B1: AED per user/year
A2: Regular Basic Price | B2: 2950
A3: DDA Shared Service Price (20% off) | B3: 2360
A4: Tier 1 - 100 to 499 | B4: 2213
A5: Tier 2 - 500 to 999 | B5: 2065
A6: Tier 3 - 1,000 to 1,999 | B6: 1770
A7: Tier 4 - 2,000 to 2,999 | B7: 1475
A8: Tier 5 - 3,000+ | B8: 1180
A9: Central Tier 5 Used in Model | B9: 1180
A11: Methodology
A12: Potential digital-signature users are planning estimates, not survey-reported headcounts.
A13: Published employee counts are used where a credible public figure was found. All other employee counts are explicitly flagged as planning estimates requiring validation.
A14: Potential users = estimated employees × addressable-user ratio. Knowledge/administrative entities use 70%; general entities 50%; field/operational entities 30%.
A15: Fragmented price assumes each entity purchases independently at the tier corresponding to its own potential user count. Central scenario applies Tier 5 AED 1,180 to all users through DDA shared service.
A16: The 5-year comparison excludes inflation, implementation/support, transaction-based products and VAT. It is a license-subscription comparison only.
A17: A second 5-year saving column compares Tier 5 directly with the AED 2,950 regular/basic price, useful as the maximum list-price saving case.
A19: Investor Upsell Assumption
A20: Adjacent products revenue uplift vs eSign | B20: 0.5
A21: Adjacent products | B21: Secure document storage, collaboration and AI
A22: Treatment | B22: Illustrative potential revenue assumption; not committed revenue
